facets_hcl-7.0.2.dist-info/licenses/LICENSE
hcl/__init__.py
hcl/__main__.py
hcl/api.py
hcl/builder.py
hcl/hcl2.lark
hcl/parser.py
hcl/py.typed
hcl/reconstructor.py
hcl/transformer.py
hcl/version.py
facets_hcl-7.0.2.dist-info/METADATA
facets_hcl-7.0.2.dist-info/WHEEL
facets_hcl-7.0.2.dist-info/entry_points.txt
facets_hcl-7.0.2.dist-info/top_level.txt
facets_hcl-7.0.2.dist-info/RECORD
