Metadata-Version: 2.4
Name: facets-hcl
Version: 7.0.2
Summary: A parser for HCL2
Author-email: Sanmesh Kakade <sanmesh.kakade@facets.cloud>
License: MIT
Project-URL: Homepage, https://github.com/Facets-cloud/python-hcl2
Classifier: Development Status :: 4 - Beta
Classifier: Topic :: Software Development :: Libraries :: Python Modules
Classifier: Intended Audience :: Developers
Classifier: License :: OSI Approved :: MIT License
Classifier: Operating System :: OS Independent
Classifier: Programming Language :: Python
Classifier: Programming Language :: Python :: 3
Classifier: Programming Language :: Python :: 3.7
Classifier: Programming Language :: Python :: 3.8
Classifier: Programming Language :: Python :: 3.9
Classifier: Programming Language :: Python :: 3.10
Classifier: Programming Language :: Python :: 3.11
Classifier: Programming Language :: Python :: 3.12
Classifier: Programming Language :: Python :: 3.13
Requires-Python: >=3.7.0
License-File: LICENSE
Requires-Dist: lark<2,>=1
Dynamic: license-file
